KassAutomate/__init__.py
KassAutomate/app/__init__.py
KassAutomate/app/App.py
KassAutomate/app/Commands.py
KassAutomate/app/Config.py
KassAutomate/app/Console.py
KassAutomate/app/Job.py
KassAutomate/app/JWT.py
KassAutomate/cli/__init__.py
KassAutomate/cli/cli.py
KassAutomate/database/migrations/2024_02_03__100619_create_users.py
KassAutomate/database/migrations/2024_02_03__101003_create_logs.py
KassAutomate/database/migrations/2024_02_03__101445_create_permissions.py
KassAutomate/database/migrations/2024_02_03__101549_create_users_permissions.py
KassAutomate/database/migrations/2024_02_03__101558_create_profiles.py
KassAutomate/database/migrations/2024_02_03__101603_create_profiles_permissions.py
KassAutomate/database/migrations/2024_02_03__103211_create_jobs.py
KassAutomate/database/migrations/2024_02_03__103740_create_job_logs.py
KassAutomate/database/models/__init__.py
KassAutomate/database/models/Job.py
KassAutomate/database/models/Joblog.py
KassAutomate/database/models/Log.py
KassAutomate/database/models/Permission.py
KassAutomate/database/models/Profile.py
KassAutomate/database/models/User.py
KassAutomate/stubs/controller.stub
kassautomate-1.0.2.dist-info/entry_points.txt
kassautomate-1.0.2.dist-info/LICENSE
kassautomate-1.0.2.dist-info/METADATA
kassautomate-1.0.2.dist-info/WHEEL
kassautomate-1.0.2.dist-info/RECORD
