Metadata-Version: 2.1
Name: KassAutomate
Version: 1.0.2
Summary: Framework Python para desenvolviemento de ETLs, RPAs, controle de processos e com uma api integrada
Author: kassiodouglas
Author-email: kass.doug@gmail.com
Requires-Python: >=3.11,<4.0
Classifier: Development Status :: 5 - Production/Stable
Classifier: Natural Language :: Portuguese (Brazilian)
Classifier: Programming Language :: Python :: 3
Classifier: Programming Language :: Python :: 3.11
Classifier: Programming Language :: Python :: 3.12
Requires-Dist: kassorm (>=1.0.15,<2.0.0)
Requires-Dist: kassstorager (>=1.0.0,<2.0.0)
